{
    "branches": [
        {
            "selector": "^in.root.demo$",
            "targets": [],
            "records": [
                {
                    "domain_name": "in.root.demo",
                    "rdata": "1.2.3.4"
                }
            ]
        },
        {
            "selector": "(subbranch|b3).demo$",
            "targets": [
                "diskdemo/subbranch.json"
            ],
            "records": []
        },
        {
            "selector": "example.org$",
            "targets": [
                "dns://8.8.8.8/"
            ],
            "records": []
        }
    ]
}
